utp/__init__.py
utp/__main__.py
utp/appVariables.py
utp/checkADB.py
utp/checkAppium.py
utp/checkJava.py
utp/checkNode.py
utp/checkRobocorp.py
utp/checkRobotFramework.py
utp/checkSuccess.py
utp/checkport.py
utp/clearArtifact.py
utp/getConfig.py
utp/localHub.py
utp/syncVersion.py
utp/utils.py
utp/utp.py
utp/utpLibrary.py
utp/utpi.py
utp/webVariables.py
universal_test_platform-0.0.83.dist-info/LICENSE.txt
universal_test_platform-0.0.83.dist-info/METADATA
universal_test_platform-0.0.83.dist-info/WHEEL
universal_test_platform-0.0.83.dist-info/entry_points.txt
universal_test_platform-0.0.83.dist-info/top_level.txt
universal_test_platform-0.0.83.dist-info/RECORD
