Metadata-Version: 2.1
Name: universal-test-platform
Version: 0.0.83
License-File: LICENSE.txt
Requires-Dist: Click
Requires-Dist: pyyaml
Requires-Dist: robotlibcore-temp
Requires-Dist: robotframework-appiumlibrary
Requires-Dist: robotframework-seleniumlibrary
Requires-Dist: requests
Requires-Dist: tqdm
